[{"namechave":"","dateE":"","dateS":"","quartos":"","pessoas":""},{"namechave":"w@a","dateE":"2022-12-14","dateS":"2022-12-20","quartos":"1","pessoas":"1"},{"namechave":"w@a","dateE":"2022-12-28","dateS":"2023-01-19","quartos":"9","pessoas":"5"},{"namechave":"w@a","dateE":"2022-12-14","dateS":"2023-02-16","quartos":"5","pessoas":"3"},{"namechave":"w@a","dateE":"2022-12-15","dateS":"2022-12-30","quartos":"2","pessoas":"2"},{"namechave":"w@a","dateE":"2022-12-15","dateS":"2023-08-08","quartos":"6","pessoas":"3"},{"namechave":"w@a","dateE":"2022-12-22","dateS":"2023-03-10","quartos":"10","pessoas":"5"},{"namechave":"w@d","dateE":"2022-12-20","dateS":"2022-12-28","quartos":"1","pessoas":"1"},{"namechave":"w@d","dateE":"2022-12-20","dateS":"2022-12-28","quartos":"1","pessoas":"1"},{"namechave":"w@d","dateE":"2022-12-20","dateS":"2022-12-28","quartos":"1","pessoas":"1"},{"namechave":"w@a","dateE":"2022-12-15","dateS":"2022-12-28","quartos":"2","pessoas":"2"},{"namechave":"w@a","dateE":"2022-12-15","dateS":"2022-12-28","quartos":"3","pessoas":"23"},{"namechave":"w@a","dateE":"2022-12-08","dateS":"","quartos":"","pessoas":""},{"namechave":"w@a","dateE":"2022-12-30","dateS":"2023-01-30","quartos":"7","pessoas":"7"},{"namechave":"w@a","dateE":"2022-12-16","dateS":"2022-12-29","quartos":"4","pessoas":"4"},{"namechave":"w@a","dateE":"2022-12-27","dateS":"2022-12-29","quartos":"44","pessoas":"44"},{"namechave":"w@a","dateE":"2022-12-22","dateS":"2022-12-21","quartos":"33","pessoas":"33"},{"namechave":"pt@22","dateE":"2022-12-16","dateS":"2022-12-22","quartos":"2","pessoas":"2"},{"namechave":"j@2","dateE":"2022-12-20","dateS":"2023-01-10","quartos":"3","pessoas":"2"}]